meta_visit_schedule/__init__.py
meta_visit_schedule/admin.py
meta_visit_schedule/apps.py
meta_visit_schedule/constants.py
meta_visit_schedule/models.py
meta_visit_schedule/migrations/__init__.py
meta_visit_schedule/tests/__init__.py
meta_visit_schedule/tests/test_schedule.py
meta_visit_schedule/tests/urls.py
meta_visit_schedule/visit_schedules/__init__.py
meta_visit_schedule/visit_schedules/crfs.py
meta_visit_schedule/visit_schedules/requisitions.py
meta_visit_schedule/visit_schedules/schedule.py
meta_visit_schedule/visit_schedules/visit_schedule.py
meta_visit_schedule-0.1.13.dist-info/AUTHORS
meta_visit_schedule-0.1.13.dist-info/LICENSE
meta_visit_schedule-0.1.13.dist-info/METADATA
meta_visit_schedule-0.1.13.dist-info/WHEEL
meta_visit_schedule-0.1.13.dist-info/top_level.txt
meta_visit_schedule-0.1.13.dist-info/RECORD
