Metadata-Version: 2.1
Name: meta-visit-schedule
Version: 0.1.13
Summary: Visit schedule for meta/edc project
Home-page: https://github.com/meta-trial/meta-visit-schedule
Author: Erik van Widenfelt
Author-email: ew2789@gmail.com
License: GPL license, see LICENSE
Keywords: meta visit schedule
Platform: UNKNOWN
Classifier: Environment :: Web Environment
Classifier: Framework :: Django
Classifier: Intended Audience :: Developers
Classifier: Intended Audience :: Science/Research
Classifier: License :: OSI Approved :: GNU General Public License v3 (GPLv3)
Classifier: Operating System :: OS Independent
Classifier: Programming Language :: Python :: 3.7
Classifier: Topic :: Internet :: WWW/HTTP
Classifier: Topic :: Internet :: WWW/HTTP :: Dynamic Content
Requires-Python: >=3.7
Requires-Dist: meta-labs
Requires-Dist: meta-sites
Requires-Dist: edc-visit-schedule
